OpenRT/__init__.py
OpenRT/eval.py
OpenRT/attacks/__init__.py
OpenRT/attacks/base_attack.py
OpenRT/attacks/blackbox/__init__.py
OpenRT/attacks/blackbox/base.py
OpenRT/attacks/blackbox/implementations/__init__.py
OpenRT/attacks/blackbox/implementations/actor_attack.py
OpenRT/attacks/blackbox/implementations/autodan.py
OpenRT/attacks/blackbox/implementations/crescendo_attack.py
OpenRT/attacks/blackbox/implementations/deepinception_attack.py
OpenRT/attacks/blackbox/implementations/direct_attack.py
OpenRT/attacks/blackbox/implementations/flipattack.py
OpenRT/attacks/blackbox/implementations/genetic_attack.py
OpenRT/attacks/blackbox/implementations/ica_attack.py
OpenRT/attacks/blackbox/implementations/iterative_base.py
OpenRT/attacks/blackbox/implementations/jailbroken_attack.py
OpenRT/attacks/blackbox/implementations/mousetrap.py
OpenRT/attacks/blackbox/implementations/multilingual_attack.py
OpenRT/attacks/blackbox/implementations/pair_attack.py
OpenRT/attacks/blackbox/implementations/prefill_attack.py
OpenRT/attacks/blackbox/implementations/rainbow_teaming.py
OpenRT/attacks/blackbox/implementations/redqueen_attack.py
OpenRT/attacks/blackbox/implementations/renellm_attack.py
OpenRT/attacks/blackbox/implementations/seqar_attack.py
OpenRT/attacks/blackbox/implementations/si_attack.py
OpenRT/attacks/blackbox/implementations/tree_attack.py
OpenRT/attacks/blackbox/implementations/xteaming_attack.py
OpenRT/attacks/blackbox/implementations/CSDJ/__init__.py
OpenRT/attacks/blackbox/implementations/CSDJ/attack.py
OpenRT/attacks/blackbox/implementations/CSDJ/image_generator.py
OpenRT/attacks/blackbox/implementations/CodeAttack/__init__.py
OpenRT/attacks/blackbox/implementations/CodeAttack/attack.py
OpenRT/attacks/blackbox/implementations/DrAttack/__init__.py
OpenRT/attacks/blackbox/implementations/DrAttack/analyzer.py
OpenRT/attacks/blackbox/implementations/DrAttack/attack.py
OpenRT/attacks/blackbox/implementations/DrAttack/core.py
openrt-0.0.2.dist-info/licenses/LICENSE
openrt-0.0.2.dist-info/METADATA
openrt-0.0.2.dist-info/WHEEL
openrt-0.0.2.dist-info/entry_points.txt
openrt-0.0.2.dist-info/top_level.txt
openrt-0.0.2.dist-info/RECORD
